{
  "patient_id": "8dc2f066-f116-0180-277f-d4670b7caa6d",
  "name": "Patient-8dc2f0",
  "age": 72,
  "gender": "M",
  "note": "Patient: Patient-8dc2f0, 72-year-old M\n              Chief Complaint:\n              . \n\n              Medical History:\n              Received higher education (finding), Full-time employment (finding), Lack of access to transportation (finding), Limited social contact (finding), Stress (finding), Full-time employment (finding), Full-time employment (finding), Full-time employment (finding), Transport problems (finding), Stress (finding), Full-time employment (finding), Victim of intimate partner abuse (finding), Stress (finding), Limited social contact (finding), Full-time employment (finding), Stress (finding), Full-time employment (finding), Full-time employment (finding), Full-time employment (finding), Stress (finding), Full-time employment (finding), Full-time employment (finding), Full-time employment (finding), Stress (finding), Victim of intimate partner abuse (finding), Full-time employment (finding), Limited social contact (finding), Full-time employment (finding), Full-time employment (finding), Victim of intimate partner abuse (finding), Full-time employment (finding), Stress (finding), Familial Alzheimer's disease of early onset (disorder), Full-time employment (finding), Social isolation (finding), Viral sinusitis (disorder), Full-time employment (finding), Stress (finding), Full-time employment (finding), Full-time employment (finding), Stress (finding), Victim of intimate partner abuse (finding), Viral sinusitis (disorder), Not in labor force (finding), Viral sinusitis (disorder), Full-time employment (finding), Full-time employment (finding), Stress (finding), Not in labor force (finding), Has a criminal record (finding), Full-time employment (finding), Limited social contact (finding), Part-time employment (finding), Social isolation (finding), Reports of violence in the environment (finding), Full-time employment (finding), Stress (finding), Pneumonia\n\n              Clinical Findings:\n              Body Height; Pain severity - 0-10 verbal numeric rating [Score] - Reported; Body Weight; Body Mass Index; Diastolic Blood Pressure\n\n              Medications:\n              Galantamine 4 MG Oral Tablet, Memantine hydrochloride 2 MG/ML Oral Solution\n\n              Plan:\n              Follow up as necessary.\n              "
}